{
  "unit": "raw_followers",
  "channels": [
    {
      "handle": "goodvibesongs",
      "ko": "굿바이브",
      "color": "#60a5fa"
    },
    {
      "handle": "goodmovies",
      "ko": "굿무비",
      "color": "#f472b6"
    },
    {
      "handle": "thishiphop",
      "ko": "디스힙합",
      "color": "#fbbf24"
    },
    {
      "handle": "readyaction",
      "ko": "레디액션",
      "color": "#34d399"
    },
    {
      "handle": "space_lab",
      "ko": "스페이스랩",
      "color": "#a78bfa"
    }
  ],
  "points": [
    {
      "date": "2026-05-27",
      "counts": [
        180000,
        85000,
        70000,
        68000,
        20000
      ]
    },
    {
      "date": "2026-05-30",
      "counts": [
        183000,
        87000,
        72000,
        71000,
        22000
      ]
    },
    {
      "date": "2026-06-02",
      "counts": [
        185000,
        88000,
        73000,
        75000,
        23000
      ]
    },
    {
      "date": "2026-06-04",
      "counts": [
        186000,
        88000,
        73000,
        77000,
        23000
      ]
    },
    {
      "date": "2026-06-05",
      "counts": [
        188000,
        89000,
        76000,
        78000,
        23000
      ]
    },
    {
      "date": "2026-06-09",
      "counts": [
        193000,
        91000,
        78000,
        81000,
        24000
      ]
    },
    {
      "date": "2026-06-10",
      "counts": [
        194000,
        92000,
        79000,
        82000,
        24000
      ]
    },
    {
      "date": "2026-06-12",
      "counts": [
        195000,
        92000,
        79000,
        83000,
        24000
      ]
    },
    {
      "date": "2026-06-15",
      "counts": [
        197000,
        94000,
        80000,
        84000,
        24000
      ]
    },
    {
      "date": "2026-06-16",
      "counts": [
        199000,
        94000,
        80000,
        84000,
        24000
      ]
    },
    {
      "date": "2026-06-17",
      "counts": [
        200000,
        94000,
        80000,
        85000,
        24000
      ]
    },
    {
      "date": "2026-06-18",
      "counts": [
        201000,
        95000,
        80000,
        85000,
        24000
      ]
    },
    {
      "date": "2026-06-19",
      "counts": [
        204000,
        95000,
        81000,
        86000,
        24000
      ]
    },
    {
      "date": "2026-06-23",
      "counts": [
        209000,
        98000,
        82000,
        88000,
        25000
      ]
    },
    {
      "date": "2026-06-24",
      "counts": [
        210855,
        98549,
        83628,
        88441,
        25242
      ]
    },
    {
      "date": "2026-06-25",
      "counts": [
        211946,
        98847,
        85817,
        92592,
        25345
      ]
    },
    {
      "date": "2026-06-26",
      "counts": [
        213038,
        99248,
        87712,
        96997,
        25408
      ]
    },
    {
      "date": "2026-06-27",
      "counts": [
        214053,
        99641,
        88383,
        98647,
        25490
      ]
    },
    {
      "date": "2026-06-28",
      "counts": [
        215471,
        99922,
        88806,
        99784,
        25595
      ]
    },
    {
      "date": "2026-06-29",
      "counts": [
        216580,
        100039,
        89147,
        100646,
        25656
      ]
    },
    {
      "date": "2026-06-30",
      "counts": [
        217065,
        100342,
        89456,
        101120,
        25685
      ]
    },
    {
      "date": "2026-07-01",
      "counts": [
        217677,
        100428,
        89764,
        101606,
        25718
      ]
    },
    {
      "date": "2026-07-02",
      "counts": [
        218661,
        100544,
        90086,
        102135,
        25842
      ]
    },
    {
      "date": "2026-07-03",
      "counts": [
        219532,
        100665,
        90507,
        102630,
        26439
      ]
    },
    {
      "date": "2026-07-04",
      "counts": [
        220272,
        100850,
        90965,
        103280,
        27404
      ]
    },
    {
      "date": "2026-07-05",
      "counts": [
        220898,
        101064,
        91297,
        103967,
        27932
      ]
    }
  ]
}
